Workbook

Sheet Resumen 1-24 meses
A1: Rentabilidad neta en los meses que pediste
A2: Comparación de los dos escenarios en los meses 1, 3, 6, 9, 12, 18 y 24. «Del mes» es lo que deja ese mes solo; «acumulado» es todo lo ganado desde el arranque. Los números salen de las hojas «Sin publicidad» y «Con publicidad» — cambiá los supuestos y esto se mueve.
A4: Mes | B4: Clientes activos (sin ads) | C4: Neto del mes (sin ads) | D4: Acumulado (sin ads) | E4: Clientes activos (con ads) | F4: Neto del mes (con ads) | G4: Acumulado (con ads) | H4: Diferencia acumulada
A5: 1 | B5: ='Sin publicidad'!D5 | C5: ='Sin publicidad'!J5 | D5: ='Sin publicidad'!K5 | E5: ='Con publicidad'!D5 | F5: ='Con publicidad'!K5 | G5: ='Con publicidad'!L5 | H5: =G5-D5
A6: 3 | B6: ='Sin publicidad'!D7 | C6: ='Sin publicidad'!J7 | D6: ='Sin publicidad'!K7 | E6: ='Con publicidad'!D7 | F6: ='Con publicidad'!K7 | G6: ='Con publicidad'!L7 | H6: =G6-D6
A7: 6 | B7: ='Sin publicidad'!D10 | C7: ='Sin publicidad'!J10 | D7: ='Sin publicidad'!K10 | E7: ='Con publicidad'!D10 | F7: ='Con publicidad'!K10 | G7: ='Con publicidad'!L10 | H7: =G7-D7
A8: 9 | B8: ='Sin publicidad'!D13 | C8: ='Sin publicidad'!J13 | D8: ='Sin publicidad'!K13 | E8: ='Con publicidad'!D13 | F8: ='Con publicidad'!K13 | G8: ='Con publicidad'!L13 | H8: =G8-D8
A9: 12 | B9: ='Sin publicidad'!D16 | C9: ='Sin publicidad'!J16 | D9: ='Sin publicidad'!K16 | E9: ='Con publicidad'!D16 | F9: ='Con publicidad'!K16 | G9: ='Con publicidad'!L16 | H9: =G9-D9
A10: 18 | B10: ='Sin publicidad'!D22 | C10: ='Sin publicidad'!J22 | D10: ='Sin publicidad'!K22 | E10: ='Con publicidad'!D22 | F10: ='Con publicidad'!K22 | G10: ='Con publicidad'!L22 | H10: =G10-D10
A11: 24 | B11: ='Sin publicidad'!D28 | C11: ='Sin publicidad'!J28 | D11: ='Sin publicidad'!K28 | E11: ='Con publicidad'!D28 | F11: ='Con publicidad'!K28 | G11: ='Con publicidad'!L28 | H11: =G11-D11
A14: Cómo leerlo
A15: · La publicidad da vuelta rápido con estos supuestos: el mes 1 cierra en pérdida (unos US$ 50 abajo), pero al mes 3 el acumulado ya es positivo y al mes 24 la diferencia contra no invertir ronda los US$ 35.000. Eso pasa porque un cliente que cuesta US$ 90 y deja US$ 57 por mes se paga solo en dos meses.
A16: · Ese resultado depende por completo de un número que todavía NO medimos: los US$ 90 por cliente. Es el supuesto más frágil de todo el modelo. Si en la práctica te sale US$ 250 —perfectamente posible con un producto sin marca conocida— la publicidad pasa a perder plata y el escenario sin ads gana. Antes de subir el gasto, gastá US$ 300 y medí cuántas ventas salieron: recién ahí este número deja de ser una apuesta.
A17: · La permanencia pesa más que el precio. Bajar las bajas del 5% al 3% mensual sube el acumulado de 24 meses más que subir el precio un 20%, y no espanta a nadie.
A18: · El plan Empresa es el que mueve la aguja: al costar más del triple, cada punto de mezcla que se corra hacia Empresa vale mucho más que un cliente nuevo de Profesional.
A19: · Esto es un modelo, no una promesa. El supuesto más frágil es «3 clientes nuevos por mes sin publicidad»: hasta que no haya un mes real con ventas, es una apuesta.

Sheet Calificación
A1: Calificación del producto, del 1 al 10
A2: Nota puesta contra lo que hoy está funcionando y probado, no contra lo que está planeado. La columna «qué falta» es lo que hay que hacer para subir cada nota, en orden de impacto.
A4: Etapa | B4: Nota | C4: Por qué esa nota | D4: Qué falta para subirla
A5: Funcionalidad (motor de ML y ETL) | B5: 8.5 | C5: DuckDB fuera de memoria sobre Parquet, tres ventanas de validación con holdout ciego, auditoría de fuga, calibración isotónica y smearing de Duan, SHAP con dirección por categoría, importancia por permutación, texto con TF-IDF, tableros con KPI automáticos y comparación contra mes anterior / año anterior / acumulado. | D5: Series de tiempo con estacionalidad, multiclase con más de 10 clases y un modo de reentrenamiento programado. Nada de eso está hoy.
A6: Pruebas y calidad | B6: 8.5 | C6: La suite corre en cada integración e incluye lo que casi nadie prueba: el .exe compilado se ejecuta de verdad en Windows (sube un archivo, entrena, calcula SHAP), y la firma del servidor web se cruza contra el verificador del programa. Cuatro errores reales los cazó el CI antes que un cliente. | D6: Falta prueba de interfaz de punta a punta (Playwright) y una prueba de carga con un dataset de varios GB.
A7: Seguridad | B7: 7.5 | C7: Licencias firmadas con Ed25519 y clave privada fuera del repositorio; token de API obligatorio en el backend local; conectores SQL de sólo lectura con barrera endurecida (sin comentarios ni literales antes de analizar, una sola sentencia, lista negra); precios del lado del servidor; el webhook de pago no le cree al aviso y consulta el estado real. | D7: El instalador no está firmado digitalmente: Windows SmartScreen va a mostrar una advertencia hasta juntar reputación (un certificado EV cuesta entre US$ 250 y 400 al año). Falta límite de intentos en las funciones del sitio, y el panel se protege con una sola contraseña sin segundo factor. El repositorio todavía es público, aunque el instalador ya no.
A8: Distribución e instalación | B8: 7 | C8: Instalador NSIS asistido: el usuario elige el disco y la carpeta, no se clava en C:. Crea acceso directo en Escritorio y Menú de inicio, deja desinstalador registrado, e instala por usuario sin pedir permisos de administrador. Se compila solo en cada integración y publica dos versiones, las dos en releases privados: la del cliente, que entrega el sitio sólo contra una licencia válida, y la de dueño. | D8: Sin firma digital, sin actualización automática dentro del programa y sin versión para macOS ni Linux. El instalador pesa 375 MB y ocupa cerca de 1,6 GB una vez instalado, por las bibliotecas de ML.
A9: Diseño del producto | B9: 7.5 | C9: Interfaz coherente en tres idiomas, tableros con filtros, tablas y gráficos interactivos exportables a Excel y CSV, KPI detectados solos, mapa de correlaciones y SHAP legibles, espacio de preguntas en lenguaje natural sobre el dataset. | D9: Falta una primera pantalla que guíe al que abre el programa por primera vez, plantillas por rubro (cobranzas, ventas, rotación) y un modo presentación para mostrarle el resultado a un gerente.
A10: Web de venta | B10: 7.5 | C10: Sitio en tres idiomas con video narrado por idioma, precios claros, cobro con MercadoPago del lado del servidor y formulario de pedido de demo que llega por correo. El instalador no se regala: se muestra en vivo y se entrega contra licencia, así que cada interesado deja nombre, empresa y correo en vez de bajar el producto y desaparecer. Todo estático: carga rápido y no cuesta nada mantenerlo. | D10: No hay dominio propio, ni prueba social (casos, logos, testimonios), ni contenido para buscadores, ni medición de visitas. Y el pedido de demo agrega fricción: convierte menos visitantes en pruebas, a cambio de que las pruebas valgan más. Hay que mirar cuántos pedidos entran por mes antes de dar por buena esa apuesta.
A11: Rentabilidad demostrada | B11: 5 | C11: El circuito de cobro está armado y probado de punta a punta: se paga, se emite la licencia, el programa la acepta. El panel muestra clientes, ingresos netos y descargas en vivo. Los costos fijos son casi cero. | D11: Cero clientes, cero facturación y ningún canal de captación andando. El producto puede cobrar; todavía no cobró. Esta nota sube sola con las primeras diez ventas.
A13: GENERAL | B13: 7.4 | C13: Producto técnicamente sólido y ya vendible, con la parte comercial sin estrenar. El motor de ML y las pruebas están por encima del promedio de lo que se vende a este precio; lo que baja el promedio es todo lo que rodea a la venta: dominio, firma del instalador, prueba social y captación. | D13: Tres cosas, en este orden: (1) las primeras diez ventas, aunque sean a conocidos; (2) dominio propio y certificado de firma; (3) tres casos reales publicados con números. Con eso la nota general va a 8,5.

Sheet Supuestos
A1: Supuestos del modelo
A2: Todo lo de esta hoja es editable. Las hojas de rentabilidad lo referencian con fórmulas: si cambiás un número acá, los 24 meses se recalculan solos.
A4: Concepto | B4: Valor | C4: Unidad | D4: De dónde sale
A5: PRECIOS Y MEZCLA
A6: Precio Profesional mensual | B6: 39 | C6: US$ | D6: El del sitio hoy
A7: Precio Empresa mensual | B7: 129 | C7: US$ | D7: El del sitio hoy
A8: Proporción de clientes en Empresa | B8: 0.2 | D8: 1 de cada 5 compra el plan caro
A9: Ingreso medio por cliente y mes | B9: =B6*(1-B8)+B7*B8 | C9: US$ | D9: Se calcula solo
A11: COBRO E IMPUESTOS
A12: Comisión de MercadoPago | B12: 0.0629 | D12: Checkout Pro con acreditación inmediata. El número real lo vas a ver en el panel, en la diferencia entre bruto y neto
A13: Tasa efectiva de impuestos | B13: 0.12 | D13: Ver la hoja «Impuestos Uruguay»: 12% es el escenario intermedio, exportando servicios y con exoneración parcial de IRAE
A15: CRECIMIENTO Y PERMANENCIA
A16: Clientes nuevos por mes sin publicidad | B16: 3 | C16: clientes | D16: Boca a boca, red propia y quien llega al sitio por su cuenta
A17: Crecimiento mensual de ese número | B17: 0.08 | D17: 8% más cada mes: llegan más porque hay más clientes hablando del producto
A18: Bajas mensuales | B18: 0.05 | D18: 5% de los activos se va cada mes. En software para empresas chicas es una cifra normal
A20: PUBLICIDAD
A21: Gasto mensual en publicidad | B21: 400 | C21: US$ | D21: Escenario con inversión
A22: Costo de conseguir un cliente | B22: 90 | C22: US$ | D22: Lo que cuesta cada venta pagada. Con producto sin marca conocida, en LATAM, es un supuesto prudente
A24: COSTOS FIJOS
A25: Vercel Pro | B25: 20 | C25: US$/mes | D25: Obligatorio en cuanto el sitio cobre: el plan gratuito es sólo para proyectos sin fines comerciales
A26: Dominio | B26: 2.5 | C26: US$/mes | D26: US$ 30 al año, prorrateado
A27: Correo (Resend) | B27: 0 | C27: US$/mes | D27: Gratis hasta 3.000 correos por mes
A28: Firma digital del instalador | B28: 27 | C28: US$/mes | D28: Certificado de firma de código: unos US$ 320 al año. Sin esto Windows muestra una advertencia al instalar
A29: Costo fijo total | B29: =SUM(B25:B28) | C29: US$/mes | D29: Se calcula solo

Sheet Sin publicidad
A1: Rentabilidad neta mes a mes — sin inversión en publicidad
A2: Todas las cifras en dólares. «Neto» es lo que queda después de la comisión de MercadoPago, los costos fijos, la publicidad y los impuestos. Las filas de los meses 1, 3, 6, 9, 12, 18 y 24 están resaltadas.
A4: Mes | B4: Clientes nuevos | C4: Bajas | D4: Clientes activos | E4: Facturación bruta | F4: Comisión MercadoPago | G4: Costos fijos | H4: Resultado antes de impuestos | I4: Impuestos | J4: RENTABILIDAD NETA | K4: Acumulado
A5: 1 | B5: =Supuestos!$B$16 | C5: 0 | D5: =B5 | E5: =D5*Supuestos!$B$9 | F5: =-E5*Supuestos!$B$12 | G5: =-Supuestos!$B$29 | H5: =E5+F5+G5 | I5: =-MAX(0,H5)*Supuestos!$B$13 | J5: =H5+I5 | K5: =J5
A6: 2 | B6: =B5*(1+Supuestos!$B$17) | C6: =D5*Supuestos!$B$18 | D6: =D5+B6-C6 | E6: =D6*Supuestos!$B$9 | F6: =-E6*Supuestos!$B$12 | G6: =-Supuestos!$B$29 | H6: =E6+F6+G6 | I6: =-MAX(0,H6)*Supuestos!$B$13 | J6: =H6+I6 | K6: =K5+J6
A7: 3 | B7: =B6*(1+Supuestos!$B$17) | C7: =D6*Supuestos!$B$18 | D7: =D6+B7-C7 | E7: =D7*Supuestos!$B$9 | F7: =-E7*Supuestos!$B$12 | G7: =-Supuestos!$B$29 | H7: =E7+F7+G7 | I7: =-MAX(0,H7)*Supuestos!$B$13 | J7: =H7+I7 | K7: =K6+J7
A8: 4 | B8: =B7*(1+Supuestos!$B$17) | C8: =D7*Supuestos!$B$18 | D8: =D7+B8-C8 | E8: =D8*Supuestos!$B$9 | F8: =-E8*Supuestos!$B$12 | G8: =-Supuestos!$B$29 | H8: =E8+F8+G8 | I8: =-MAX(0,H8)*Supuestos!$B$13 | J8: =H8+I8 | K8: =K7+J8
A9: 5 | B9: =B8*(1+Supuestos!$B$17) | C9: =D8*Supuestos!$B$18 | D9: =D8+B9-C9 | E9: =D9*Supuestos!$B$9 | F9: =-E9*Supuestos!$B$12 | G9: =-Supuestos!$B$29 | H9: =E9+F9+G9 | I9: =-MAX(0,H9)*Supuestos!$B$13 | J9: =H9+I9 | K9: =K8+J9
A10: 6 | B10: =B9*(1+Supuestos!$B$17) | C10: =D9*Supuestos!$B$18 | D10: =D9+B10-C10 | E10: =D10*Supuestos!$B$9 | F10: =-E10*Supuestos!$B$12 | G10: =-Supuestos!$B$29 | H10: =E10+F10+G10 | I10: =-MAX(0,H10)*Supuestos!$B$13 | J10: =H10+I10 | K10: =K9+J10
A11: 7 | B11: =B10*(1+Supuestos!$B$17) | C11: =D10*Supuestos!$B$18 | D11: =D10+B11-C11 | E11: =D11*Supuestos!$B$9 | F11: =-E11*Supuestos!$B$12 | G11: =-Supuestos!$B$29 | H11: =E11+F11+G11 | I11: =-MAX(0,H11)*Supuestos!$B$13 | J11: =H11+I11 | K11: =K10+J11
A12: 8 | B12: =B11*(1+Supuestos!$B$17) | C12: =D11*Supuestos!$B$18 | D12: =D11+B12-C12 | E12: =D12*Supuestos!$B$9 | F12: =-E12*Supuestos!$B$12 | G12: =-Supuestos!$B$29 | H12: =E12+F12+G12 | I12: =-MAX(0,H12)*Supuestos!$B$13 | J12: =H12+I12 | K12: =K11+J12
A13: 9 | B13: =B12*(1+Supuestos!$B$17) | C13: =D12*Supuestos!$B$18 | D13: =D12+B13-C13 | E13: =D13*Supuestos!$B$9 | F13: =-E13*Supuestos!$B$12 | G13: =-Supuestos!$B$29 | H13: =E13+F13+G13 | I13: =-MAX(0,H13)*Supuestos!$B$13 | J13: =H13+I13 | K13: =K12+J13
A14: 10 | B14: =B13*(1+Supuestos!$B$17) | C14: =D13*Supuestos!$B$18 | D14: =D13+B14-C14 | E14: =D14*Supuestos!$B$9 | F14: =-E14*Supuestos!$B$12 | G14: =-Supuestos!$B$29 | H14: =E14+F14+G14 | I14: =-MAX(0,H14)*Supuestos!$B$13 | J14: =H14+I14 | K14: =K13+J14
A15: 11 | B15: =B14*(1+Supuestos!$B$17) | C15: =D14*Supuestos!$B$18 | D15: =D14+B15-C15 | E15: =D15*Supuestos!$B$9 | F15: =-E15*Supuestos!$B$12 | G15: =-Supuestos!$B$29 | H15: =E15+F15+G15 | I15: =-MAX(0,H15)*Supuestos!$B$13 | J15: =H15+I15 | K15: =K14+J15
A16: 12 | B16: =B15*(1+Supuestos!$B$17) | C16: =D15*Supuestos!$B$18 | D16: =D15+B16-C16 | E16: =D16*Supuestos!$B$9 | F16: =-E16*Supuestos!$B$12 | G16: =-Supuestos!$B$29 | H16: =E16+F16+G16 | I16: =-MAX(0,H16)*Supuestos!$B$13 | J16: =H16+I16 | K16: =K15+J16
A17: 13 | B17: =B16*(1+Supuestos!$B$17) | C17: =D16*Supuestos!$B$18 | D17: =D16+B17-C17 | E17: =D17*Supuestos!$B$9 | F17: =-E17*Supuestos!$B$12 | G17: =-Supuestos!$B$29 | H17: =E17+F17+G17 | I17: =-MAX(0,H17)*Supuestos!$B$13 | J17: =H17+I17 | K17: =K16+J17
... A28: 24 | B28: =B27*(1+Supuestos!$B$17) | C28: =D27*Supuestos!$B$18 | D28: =D27+B28-C28 | E28: =D28*Supuestos!$B$9 | F28: =-E28*Supuestos!$B$12 | G28: =-Supuestos!$B$29 | H28: =E28+F28+G28 | I28: =-MAX(0,H28)*Supuestos!$B$13 | J28: =H28+I28 | K28: =K27+J28

Sheet Con publicidad
A1: Rentabilidad neta mes a mes — con inversión en publicidad
A2: Todas las cifras en dólares. «Neto» es lo que queda después de la comisión de MercadoPago, los costos fijos, la publicidad y los impuestos. Las filas de los meses 1, 3, 6, 9, 12, 18 y 24 están resaltadas.
A4: Mes | B4: Clientes nuevos | C4: Bajas | D4: Clientes activos | E4: Facturación bruta | F4: Comisión MercadoPago | G4: Costos fijos | H4: Publicidad | I4: Resultado antes de impuestos | J4: Impuestos | K4: RENTABILIDAD NETA | L4: Acumulado
A5: 1 | B5: =Supuestos!$B$16+Supuestos!$B$21/Supuestos!$B$22 | C5: 0 | D5: =B5 | E5: =D5*Supuestos!$B$9 | F5: =-E5*Supuestos!$B$12 | G5: =-Supuestos!$B$29 | H5: =-Supuestos!$B$21 | I5: =E5+F5+G5+H5 | J5: =-MAX(0,I5)*Supuestos!$B$13 | K5: =I5+J5 | L5: =K5
A6: 2 | B6: =(B5-Supuestos!$B$21/Supuestos!$B$22)*(1+Supuestos!$B$17)+Supuestos!$B$21/Supuestos!$B$22 | C6: =D5*Supuestos!$B$18 | D6: =D5+B6-C6 | E6: =D6*Supuestos!$B$9 | F6: =-E6*Supuestos!$B$12 | G6: =-Supuestos!$B$29 | H6: =-Supuestos!$B$21 | I6: =E6+F6+G6+H6 | J6: =-MAX(0,I6)*Supuestos!$B$13 | K6: =I6+J6 | L6: =L5+K6
A7: 3 | B7: =(B6-Supuestos!$B$21/Supuestos!$B$22)*(1+Supuestos!$B$17)+Supuestos!$B$21/Supuestos!$B$22 | C7: =D6*Supuestos!$B$18 | D7: =D6+B7-C7 | E7: =D7*Supuestos!$B$9 | F7: =-E7*Supuestos!$B$12 | G7: =-Supuestos!$B$29 | H7: =-Supuestos!$B$21 | I7: =E7+F7+G7+H7 | J7: =-MAX(0,I7)*Supuestos!$B$13 | K7: =I7+J7 | L7: =L6+K7
A8: 4 | B8: =(B7-Supuestos!$B$21/Supuestos!$B$22)*(1+Supuestos!$B$17)+Supuestos!$B$21/Supuestos!$B$22 | C8: =D7*Supuestos!$B$18 | D8: =D7+B8-C8 | E8: =D8*Supuestos!$B$9 | F8: =-E8*Supuestos!$B$12 | G8: =-Supuestos!$B$29 | H8: =-Supuestos!$B$21 | I8: =E8+F8+G8+H8 | J8: =-MAX(0,I8)*Supuestos!$B$13 | K8: =I8+J8 | L8: =L7+K8
A9: 5 | B9: =(B8-Supuestos!$B$21/Supuestos!$B$22)*(1+Supuestos!$B$17)+Supuestos!$B$21/Supuestos!$B$22 | C9: =D8*Supuestos!$B$18 | D9: =D8+B9-C9 | E9: =D9*Supuestos!$B$9 | F9: =-E9*Supuestos!$B$12 | G9: =-Supuestos!$B$29 | H9: =-Supuestos!$B$21 | I9: =E9+F9+G9+H9 | J9: =-MAX(0,I9)*Supuestos!$B$13 | K9: =I9+J9 | L9: =L8+K9
A10: 6 | B10: =(B9-Supuestos!$B$21/Supuestos!$B$22)*(1+Supuestos!$B$17)+Supuestos!$B$21/Supuestos!$B$22 | C10: =D9*Supuestos!$B$18 | D10: =D9+B10-C10 | E10: =D10*Supuestos!$B$9 | F10: =-E10*Supuestos!$B$12 | G10: =-Supuestos!$B$29 | H10: =-Supuestos!$B$21 | I10: =E10+F10+G10+H10 | J10: =-MAX(0,I10)*Supuestos!$B$13 | K10: =I10+J10 | L10: =L9+K10
A11: 7 | B11: =(B10-Supuestos!$B$21/Supuestos!$B$22)*(1+Supuestos!$B$17)+Supuestos!$B$21/Supuestos!$B$22 | C11: =D10*Supuestos!$B$18 | D11: =D10+B11-C11 | E11: =D11*Supuestos!$B$9 | F11: =-E11*Supuestos!$B$12 | G11: =-Supuestos!$B$29 | H11: =-Supuestos!$B$21 | I11: =E11+F11+G11+H11 | J11: =-MAX(0,I11)*Supuestos!$B$13 | K11: =I11+J11 | L11: =L10+K11
A12: 8 | B12: =(B11-Supuestos!$B$21/Supuestos!$B$22)*(1+Supuestos!$B$17)+Supuestos!$B$21/Supuestos!$B$22 | C12: =D11*Supuestos!$B$18 | D12: =D11+B12-C12 | E12: =D12*Supuestos!$B$9 | F12: =-E12*Supuestos!$B$12 | G12: =-Supuestos!$B$29 | H12: =-Supuestos!$B$21 | I12: =E12+F12+G12+H12 | J12: =-MAX(0,I12)*Supuestos!$B$13 | K12: =I12+J12 | L12: =L11+K12
A13: 9 | B13: =(B12-Supuestos!$B$21/Supuestos!$B$22)*(1+Supuestos!$B$17)+Supuestos!$B$21/Supuestos!$B$22 | C13: =D12*Supuestos!$B$18 | D13: =D12+B13-C13 | E13: =D13*Supuestos!$B$9 | F13: =-E13*Supuestos!$B$12 | G13: =-Supuestos!$B$29 | H13: =-Supuestos!$B$21 | I13: =E13+F13+G13+H13 | J13: =-MAX(0,I13)*Supuestos!$B$13 | K13: =I13+J13 | L13: =L12+K13
A14: 10 | B14: =(B13-Supuestos!$B$21/Supuestos!$B$22)*(1+Supuestos!$B$17)+Supuestos!$B$21/Supuestos!$B$22 | C14: =D13*Supuestos!$B$18 | D14: =D13+B14-C14 | E14: =D14*Supuestos!$B$9 | F14: =-E14*Supuestos!$B$12 | G14: =-Supuestos!$B$29 | H14: =-Supuestos!$B$21 | I14: =E14+F14+G14+H14 | J14: =-MAX(0,I14)*Supuestos!$B$13 | K14: =I14+J14 | L14: =L13+K14
A15: 11 | B15: =(B14-Supuestos!$B$21/Supuestos!$B$22)*(1+Supuestos!$B$17)+Supuestos!$B$21/Supuestos!$B$22 | C15: =D14*Supuestos!$B$18 | D15: =D14+B15-C15 | E15: =D15*Supuestos!$B$9 | F15: =-E15*Supuestos!$B$12 | G15: =-Supuestos!$B$29 | H15: =-Supuestos!$B$21 | I15: =E15+F15+G15+H15 | J15: =-MAX(0,I15)*Supuestos!$B$13 | K15: =I15+J15 | L15: =L14+K15
A16: 12 | B16: =(B15-Supuestos!$B$21/Supuestos!$B$22)*(1+Supuestos!$B$17)+Supuestos!$B$21/Supuestos!$B$22 | C16: =D15*Supuestos!$B$18 | D16: =D15+B16-C16 | E16: =D16*Supuestos!$B$9 | F16: =-E16*Supuestos!$B$12 | G16: =-Supuestos!$B$29 | H16: =-Supuestos!$B$21 | I16: =E16+F16+G16+H16 | J16: =-MAX(0,I16)*Supuestos!$B$13 | K16: =I16+J16 | L16: =L15+K16
A17: 13 | B17: =(B16-Supuestos!$B$21/Supuestos!$B$22)*(1+Supuestos!$B$17)+Supuestos!$B$21/Supuestos!$B$22 | C17: =D16*Supuestos!$B$18 | D17: =D16+B17-C17 | E17: =D17*Supuestos!$B$9 | F17: =-E17*Supuestos!$B$12 | G17: =-Supuestos!$B$29 | H17: =-Supuestos!$B$21 | I17: =E17+F17+G17+H17 | J17: =-MAX(0,I17)*Supuestos!$B$13 | K17: =I17+J17 | L17: =L16+K17
... A28: 24 | B28: =(B27-Supuestos!$B$21/Supuestos!$B$22)*(1+Supuestos!$B$17)+Supuestos!$B$21/Supuestos!$B$22 | C28: =D27*Supuestos!$B$18 | D28: =D27+B28-C28 | E28: =D28*Supuestos!$B$9 | F28: =-E28*Supuestos!$B$12 | G28: =-Supuestos!$B$29 | H28: =-Supuestos!$B$21 | I28: =E28+F28+G28+H28 | J28: =-MAX(0,I28)*Supuestos!$B$13 | K28: =I28+J28 | L28: =L27+K28

Sheet Impuestos Uruguay
A1: Cuánto se lleva el fisco, según cómo factures
A2: Cuatro caminos posibles, del más chico al más armado. La columna de la derecha es la que hay que llevar a la hoja «Supuestos», en «Tasa efectiva de impuestos».
A4: Régimen | B4: Qué es | C4: Qué se paga | D4: Tasa efectiva sobre facturación | E4: Cuándo conviene
A5: Unipersonal — Literal E | B5: Facturación anual chica (hasta el tope que fija la DGI, del orden de UYU 1.100.000 por año). Se paga un importe fijo mensual por IVA mínimo e IRAE ficto, más los aportes a BPS del titular. | C5: Muy baja: el fijo mensual ronda el equivalente a US$ 130-180 entre DGI y BPS. | D5: ≈ 6-10% de la facturación mientras seas chico; el porcentaje baja cuanto más facturás. | E5: Es donde conviene arrancar. Cuando pases el tope hay que cambiar de régimen sí o sí.
A6: Sociedad (SAS o SRL) — régimen general | B6: IRAE 25% sobre la renta neta (ingresos menos gastos deducibles), IVA 22% sobre las ventas dentro de Uruguay, y 7% de IRPF/IRNR cuando se reparten dividendos. | C6: IRAE 25% + IVA 22% en ventas locales + 7% al retirar. | D6: ≈ 25-30% sobre la ganancia si vendés dentro del país. | E6: Es el escenario caro. Sólo tiene sentido si la mayor parte de las ventas son locales y ya son grandes.
A7: Sociedad exportando servicios | B7: La venta de software a un cliente del exterior, usado en el exterior, se trata como exportación de servicios: no lleva IVA. Queda el IRAE sobre la renta neta. | C7: Sin IVA en esas ventas. IRAE 25% sobre la ganancia. | D7: ≈ 12-18% sobre la facturación, según cuánto gasto tengas para deducir. | E7: Es el escenario más probable para este producto: el mercado natural es LATAM y el mundo, no sólo Uruguay.
A8: Sociedad con exoneración de software | B8: Uruguay exonera de IRAE la renta por producción de soporte lógico desarrollado en el país, cumpliendo requisitos de nexo (proporción del gasto en desarrollo local y personal calificado) y registro. | C8: IRAE puede quedar cerca de 0 sobre la parte exonerada. IVA exportación sigue sin aplicar. | D8: ≈ 3-8% sobre la facturación, casi todo BPS y gastos administrativos. | E8: Es el mejor escenario y es alcanzable, pero exige cumplir los requisitos formales y tener el registro al día. Sin contador no lo armes.
A10: ADVERTENCIA. Los porcentajes de esta hoja son órdenes de magnitud para armar el modelo, no asesoramiento fiscal. Los topes, las tasas y los requisitos de la exoneración de software cambian, y el que decide qué régimen te corresponde es un contador con tus números adelante. Antes de facturar la primera venta, sentate una hora con uno: cuesta poco y te ahorra elegir mal el régimen, que después es caro de revertir.

Sheet Competencia
A1: Contra quién se compite, por mercado
A2: Los precios son órdenes de magnitud tomados de la comunicación pública de cada producto y cambian seguido: verificalos antes de usarlos en una propuesta comercial. La última columna es lo que hay que decir en una reunión cuando aparece ese nombre.
A4: Mercado | B4: Competidor | C4: Qué hace | D4: Precio aproximado | E4: Su fortaleza | F4: Su debilidad | G4: Cómo se le gana
A5: Uruguay | B5: Consultoras de datos locales | C5: Proyectos a medida: un analista arma el modelo y entrega un informe. | D5: US$ 3.000 a 15.000 por proyecto | E5: Confianza, trato cara a cara, entienden el negocio local. | F5: No dejan herramienta: cuando termina el proyecto, la empresa vuelve a depender de ellos para el próximo. | G5: MV cuesta una fracción y queda instalado. Se puede vender incluso a la consultora, como herramienta para entregar más rápido.
A6: Uruguay | B6: Power BI / Tableau con un analista | C6: Tableros y reportes. Predicción, poco y nada. | D6: US$ 14 por usuario/mes + sueldo del analista | E6: Ya está instalado en casi todas las empresas medianas; nadie discute la compra. | F6: Describe el pasado. Para predecir hay que salir de la herramienta. | G6: MV no compite: se enchufa al lado. El discurso es «esto te dice qué va a pasar, no qué pasó».
A7: Uruguay | B7: Desarrollador freelance | C7: Scripts de Python a medida, entregados como notebook. | D7: US$ 25 a 60 la hora | E7: Barato y flexible. | F7: Sin validación seria, sin control de fuga, sin mantenimiento. El modelo se pudre en tres meses y nadie lo nota. | G7: Ahí está la ventaja más defendible de MV: tres ventanas de validación y auditoría de fuga, o sea números en los que se puede confiar.
A8: LATAM | B8: Pecan.ai | C8: AutoML predictivo apuntado a marketing y retención, en la nube. | D8: Empresarial, del orden de US$ 2.000+ por mes | E8: Muy pulido, buena narrativa comercial. | F8: Caro para el bolsillo de la empresa mediana de la región, y los datos van a la nube. | G8: MV corre en la máquina del cliente y cuesta 50 veces menos. Para un banco o una financiera, que los datos no salgan es un argumento de venta enorme.
A9: LATAM | B9: Nubes regionales (Vertex AI, SageMaker, Azure ML) | C9: AutoML por consumo dentro de la nube del proveedor. | D9: Por uso: de US$ 50 a miles por mes | E9: Escala infinita, integración con el resto de la nube. | F9: Requiere un equipo que sepa usarlas. La factura es impredecible. Los datos se suben. | G9: MV es precio fijo, sin factura sorpresa, sin subir nada y sin equipo de datos.
A10: LATAM | B10: BI regional + consultoría (SAS, Qlik y socios locales) | C10: Licencia más implementación por integrador. | D10: US$ 10.000 a 100.000 por año | E10: Relación instalada con las empresas grandes. | F10: Ciclo de venta larguísimo, implementación de meses. | G10: MV entra por abajo: se instala en una tarde y da resultado el mismo día.
A11: Mundo | B11: DataRobot | C11: La plataforma de AutoML empresarial de referencia. | D11: Del orden de US$ 50.000+ por año | E11: Completísima, gobernanza, MLOps, soporte. | F11: Precio de otro planeta para una PyME. Implementación pesada. | G11: No se compite de frente. MV es «el DataRobot que sí podés pagar», con el 20% de las funciones que el 90% de las empresas usa.
A12: Mundo | B12: H2O Driverless AI | C12: AutoML potente, en la nube o instalado. | D12: Decenas de miles de dólares por año | E12: Motor técnicamente muy bueno. | F12: Curva de aprendizaje y precio empresarial. | G12: MV apunta al usuario que no es científico de datos: se elige el objetivo y listo.
A13: Mundo | B13: Dataiku | C13: Plataforma colaborativa de datos y ML. | D13: Edición gratuita limitada; empresarial de cinco cifras | E13: Cubre todo el ciclo, muy adoptada. | F13: Necesita un equipo. Pensada para organizaciones con área de datos. | G13: MV es de una sola persona: el gerente que quiere una respuesta, sin equipo.
A14: Mundo | B14: KNIME / Orange (código abierto) | C14: Flujos visuales de análisis y ML, gratis. | D14: Gratis el escritorio; Hub pago | E14: Cuestan cero y son muy capaces. | F14: Hay que saber armar el flujo. No traen validación honesta de fábrica ni tableros de negocio. | G14: El competidor más incómodo, porque el precio es imbatible. MV gana en tiempo hasta el resultado y en que la validación viene puesta, no hay que saber armarla.
A15: Mundo | B15: Obviously.AI, Akkio y similares | C15: AutoML web sin código, por suscripción mensual. | D15: US$ 75 a 1.500 por mes | E15: Simplísimos de usar, muy buen precio de entrada. | F15: En la nube, con topes de filas, y poco control sobre la validación. | G15: Es el competidor más parecido en precio. MV se diferencia en tres cosas: corre local, no tiene tope de filas en el plan pago, y muestra el holdout ciego.
A16: Mundo | B16: Alteryx Designer | C16: Preparación de datos y análisis para el analista de negocio. | D16: ≈ US$ 5.000 por usuario y año | E16: Estándar en muchas áreas de finanzas y operaciones. | F16: Caro por usuario; el ML es secundario. | G16: MV cubre la parte de ML a una fracción, y el ETL automático le compite de frente.
A18: Dónde está el lugar de MV AutoML Studio
A19: · Arriba está lo empresarial (DataRobot, H2O, Dataiku): potentísimo y a partir de cinco cifras al año. Abajo está lo gratuito (KNIME, Orange): capaz, pero hay que saber armarlo. En el medio quedan las herramientas web por suscripción, que son fáciles pero suben tus datos a la nube ajena.
A20: · El hueco es ese: una PyME o un área de riesgo/cobranzas que quiere predecir, no tiene equipo de datos, no puede pagar cinco cifras y NO PUEDE subir los datos de sus clientes a un servidor de otro. Ahí no hay casi nadie a US$ 39 por mes.
A21: · Los tres argumentos que hay que repetir siempre: (1) tus datos no salen de tu computadora; (2) te muestra el resultado sobre datos que el modelo nunca vio, así que el número no está inflado; (3) lo usa el que decide, no hace falta un científico de datos.
A22: · El riesgo real no es DataRobot: es que la empresa siga usando la planilla de Excel de siempre. La venta se gana mostrando un caso propio de ellos, con sus datos, en la primera reunión.
